pykubegrader/__init__.py
pykubegrader/grading_tester.ipynb
pykubegrader/initialize.py
pykubegrader/telemetry.py
pykubegrader/utils.py
pykubegrader/validate.py
pykubegrader/build/__init__.py
pykubegrader/build/api_notebook_builder.py
pykubegrader/build/build_folder.py
pykubegrader/build/clean_folder.py
pykubegrader/build/collate.py
pykubegrader/build/markdown_questions.py
pykubegrader/grade_reports/__grade_reports.py
pykubegrader/grade_reports/assignments.py
pykubegrader/grade_reports/class_grade_report.py
pykubegrader/grade_reports/grade_report.py
pykubegrader/grade_reports/grading_config.py
pykubegrader/grade_reports/test.ipynb
pykubegrader/graders/__init__.py
pykubegrader/graders/late_assignments.py
pykubegrader/log_parser/__init__.py
pykubegrader/log_parser/parse.ipynb
pykubegrader/log_parser/parse.py
pykubegrader/submit/submit_assignment.py
pykubegrader/tokens/generator.py
pykubegrader/tokens/token_panel.py
pykubegrader/tokens/tokens.py
pykubegrader/tokens/validate_token.py
pykubegrader/widgets/__init__.py
pykubegrader/widgets/multiple_choice.py
pykubegrader/widgets/question_processor.py
pykubegrader/widgets/reading_question.py
pykubegrader/widgets/select_many.py
pykubegrader/widgets/student_info.py
pykubegrader/widgets/style.py
pykubegrader/widgets/true_false.py
pykubegrader/widgets/types_question.py
pykubegrader/widgets_base/__init__.py
pykubegrader/widgets_base/multi_select.py
pykubegrader/widgets_base/reading.py
pykubegrader/widgets_base/select.py
pykubegrader-0.3.18.dist-info/LICENSE.txt
pykubegrader-0.3.18.dist-info/METADATA
pykubegrader-0.3.18.dist-info/WHEEL
pykubegrader-0.3.18.dist-info/entry_points.txt
pykubegrader-0.3.18.dist-info/top_level.txt
pykubegrader-0.3.18.dist-info/RECORD
