Metadata-Version: 2.2
Name: PyKubeGrader
Version: 0.3.18
Summary: Add a short description here!
Home-page: https://github.com/pyscaffold/pyscaffold/
Author: jagar2
Author-email: jca92@drexel.edu
License: MIT
Project-URL: Documentation, https://pyscaffold.org/
Platform: any
Classifier: Development Status :: 4 - Beta
Classifier: Programming Language :: Python
License-File: LICENSE.txt
Requires-Dist: importlib-metadata; python_version < "3.8"
Requires-Dist: ipython
Requires-Dist: mypy
Requires-Dist: nbformat
Requires-Dist: numpy
Requires-Dist: pandas-stubs
Requires-Dist: panel
Requires-Dist: pynacl
Requires-Dist: pytest
Requires-Dist: requests
Requires-Dist: ruff
Requires-Dist: setuptools
Requires-Dist: sphinx
Requires-Dist: types-python-dateutil
Requires-Dist: types-pyyaml
Requires-Dist: types-requests
Requires-Dist: types-setuptools
Provides-Extra: testing
Requires-Dist: setuptools; extra == "testing"
Requires-Dist: pytest; extra == "testing"
Requires-Dist: pytest-cov; extra == "testing"
